text_processor_nlp/__init__.py
text_processor_nlp-0.1.dist-info/METADATA
text_processor_nlp-0.1.dist-info/WHEEL
text_processor_nlp-0.1.dist-info/top_level.txt
text_processor_nlp-0.1.dist-info/RECORD
