Metadata-Version: 2.1
Name: text-processor-nlp
Version: 0.1
Summary: A short description of the package
Home-page: https://github.com/SiddiqueFarhan/pypi_demo
Author: Farhan Siddiqui
Author-email: Farhan.siddiqui1572@gmail.com
Classifier: Programming Language :: Python :: 3
Classifier: License :: OSI Approved :: MIT License
Classifier: Operating System :: OS Independent
Requires-Dist: spacy (>=3.0.0)
